{"cameraMode":{"drawMode":0,"name":"Shaded","section":"Shading Mode"},"sceneLighting":true,"audioPlay":false,"sceneViewState":{"m_AlwaysRefresh":false,"showFog":true,"showSkybox":true,"showFlares":true,"showImageEffects":true,"showParticleSystems":true,"showVisualEffectGraphs":true,"m_FxEnabled":true},"in2DMode":false,"pivot":{"x":-1184.72509765625,"y":51.154293060302737,"z":39.25022506713867},"rotation":{"x":-0.2973324954509735,"y":0.6443871259689331,"z":-0.30097246170043948,"w":-0.6370910406112671},"size":14.458518981933594,"orthographic":false}